justlog/classes.py
justlog/formatter.py
justlog/justlog.py
justlog/settings.py
justlog-0.1.0.dist-info/LICENSE
justlog-0.1.0.dist-info/METADATA
justlog-0.1.0.dist-info/WHEEL
justlog-0.1.0.dist-info/top_level.txt
justlog-0.1.0.dist-info/RECORD
