Metadata-Version: 2.1
Name: justlog
Version: 0.1.0
Summary: A simple logging library for Python 3
Home-page: https://github.com/Gabisonfire/justlog
Author: Gabisonfire
Author-email: gabisonfire@github.com
License: UNKNOWN
Keywords: logging json simple http tcp quick logs
Platform: UNKNOWN
Classifier: Programming Language :: Python :: 3
Classifier: License :: OSI Approved :: MIT License
Classifier: Operating System :: OS Independent
Requires-Python: >=3.*
Requires-Dist: colorama
Requires-Dist: requests
